{"dependencies":[{"name":"../../Observable","loc":{"line":2,"column":27}},{"name":"../../operator/debounce","loc":{"line":3,"column":25}}],"generated":{"js":"\"use strict\";\nvar Observable_1 = require('../../Observable');\nvar debounce_1 = require('../../operator/debounce');\nObservable_1.Observable.prototype.debounce = debounce_1.debounce;\n//# sourceMappingURL=debounce.js.map","map":{"mappings":[{"source":"node_modules/rxjs/add/operator/debounce.js","original":{"line":1,"column":0},"generated":{"line":1,"column":0}},{"source":"node_modules/rxjs/add/operator/debounce.js","original":{"line":2,"column":0},"generated":{"line":2,"column":0}},{"source":"node_modules/rxjs/add/operator/debounce.js","original":{"line":3,"column":0},"generated":{"line":3,"column":0}},{"source":"node_modules/rxjs/add/operator/debounce.js","original":{"line":4,"column":0},"generated":{"line":4,"column":0}},{"source":"node_modules/rxjs/add/operator/debounce.js","original":{"line":5,"column":0},"generated":{"line":5,"column":0}}],"sources":{"node_modules/rxjs/add/operator/debounce.js":"\"use strict\";\nvar Observable_1 = require('../../Observable');\nvar debounce_1 = require('../../operator/debounce');\nObservable_1.Observable.prototype.debounce = debounce_1.debounce;\n//# sourceMappingURL=debounce.js.map"},"lineCount":5}},"hash":"9e271e0a6903a0c370a92e744f1900d6","cacheData":{"env":{}}}